opendatasets/__init__.py
opendatasets/_version.py
opendatasets/datasets/__init__.py
opendatasets/datasets/countries-languages-spoken/__init__.py
opendatasets/datasets/owid-covid-19-latest/__init__.py
opendatasets/datasets/stackoverflow-developer-survey-2020/__init__.py
opendatasets/datasets/state-of-javascript-2016/__init__.py
opendatasets/datasets/state-of-javascript-2017/__init__.py
opendatasets/datasets/state-of-javascript-2018/__init__.py
opendatasets/datasets/state-of-javascript-2019/__init__.py
opendatasets/utils/__init__.py
opendatasets/utils/archive.py
opendatasets/utils/googledrive.py
opendatasets/utils/kaggle_api.py
opendatasets/utils/kaggle_direct.py
opendatasets/utils/md5.py
opendatasets/utils/network.py
opendatasets-0.1.22.dist-info/LICENSE
opendatasets-0.1.22.dist-info/METADATA
opendatasets-0.1.22.dist-info/WHEEL
opendatasets-0.1.22.dist-info/top_level.txt
opendatasets-0.1.22.dist-info/RECORD
