Metadata-Version: 2.1
Name: opendatasets
Version: 0.1.22
Summary: A curated collection of datasets for data analysis & machine learning, downloadable with a single Python command
Home-page: https://github.com/JovianML/opendatasets
Author: Jovian.ml
Author-email: hello@jovian.ml
License: UNKNOWN
Platform: UNKNOWN
Classifier: Programming Language :: Python :: 3
Classifier: License :: OSI Approved :: MIT License
Classifier: Operating System :: OS Independent
